trame/modules/flow.py
trame/widgets/flow.py
trame_flow/__init__.py
trame_flow/module/__init__.py
trame_flow/module/core.py
trame_flow/module/serve/style.css
trame_flow/module/serve/trame_flow.umd.js
trame_flow/widgets/__init__.py
trame_flow/widgets/flow/__init__.py
trame_flow/widgets/flow/background.py
trame_flow/widgets/flow/common.py
trame_flow/widgets/flow/controls.py
trame_flow/widgets/flow/minimap.py
trame_flow/widgets/flow/node_editor.py
trame_flow/widgets/flow/node_resizer.py
trame_flow/widgets/flow/node_toolbar.py
trame_flow-2.0.0.dist-info/METADATA
trame_flow-2.0.0.dist-info/WHEEL
trame_flow-2.0.0.dist-info/licenses/LICENSE
trame_flow-2.0.0.dist-info/RECORD
