Metadata-Version: 2.4
Name: trame-flow
Version: 2.0.0
Summary: A node editor for trame using VueFlow
Author: Trame Developer
License: MIT License
License-File: LICENSE
Keywords: Application,Framework,Interactive,Python,Web
Classifier: Development Status :: 4 - Beta
Classifier: Environment :: Web Environment
Classifier: License :: OSI Approved :: MIT License
Classifier: Natural Language :: English
Classifier: Operating System :: OS Independent
Classifier: Programming Language :: Python :: 3 :: Only
Classifier: Topic :: Software Development :: Libraries :: Application Frameworks
Classifier: Topic :: Software Development :: Libraries :: Python Modules
Requires-Python: >=3.9
Requires-Dist: trame-client>=3.10
Requires-Dist: typing-extensions>=4.10.0
Provides-Extra: app
Requires-Dist: pywebview; extra == 'app'
Provides-Extra: dev
Requires-Dist: nox; extra == 'dev'
Requires-Dist: pre-commit; extra == 'dev'
Requires-Dist: pytest-cov>=3; extra == 'dev'
Requires-Dist: pytest>=6; extra == 'dev'
Requires-Dist: ruff; extra == 'dev'
Provides-Extra: examples
Requires-Dist: trame-vuetify>=3.1.0; extra == 'examples'
Requires-Dist: trame>=3.12.0; extra == 'examples'
Provides-Extra: jupyter
Requires-Dist: jupyterlab; extra == 'jupyter'
